LICENSE
MANIFEST.in
README.md
setup.cfg
setup.py
cube_helper/__init__.py
cube_helper/cube_equaliser.py
cube_helper/cube_help.py
cube_helper/cube_loader.py
cube_helper/fix_known.py
cube_helper/logger.py
cube_helper.egg-info/PKG-INFO
cube_helper.egg-info/SOURCES.txt
cube_helper.egg-info/dependency_links.txt
cube_helper.egg-info/requires.txt
cube_helper.egg-info/top_level.txt