Metadata-Version: 2.1
Name: cube-helper
Version: 2.2.3
Summary: Cube Helper is a package to make equalisation, concatenation, and analysis of Iris cubes easier.
Home-page: https://github.com/MetOffice/cube_helper
Author: Met Office
Author-email: jon.seddon@metoffice.gov.uk
License: BSD 3-Clause License
Download-URL: https://github.com/MetOffice/cube_helper/releases
Keywords: climate,cmip,iris,cubes,preprocessing
Platform: UNKNOWN
Classifier: Development Status :: 5 - Production/Stable
Classifier: License :: OSI Approved :: BSD License
Classifier: Natural Language :: English
Classifier: Topic :: Scientific/Engineering :: Atmospheric Science
Classifier: Programming Language :: Python :: 2.7
Classifier: Programming Language :: Python :: 3.6
Classifier: Programming Language :: Python :: 3.7
Classifier: Programming Language :: Python :: 3.8
License-File: LICENSE
